sqleval/__init__.py
sqleval/agent.py
sqleval/evaluator.py
sqleval/result.py
sqleval-0.2.0.dist-info/LICENSE
sqleval-0.2.0.dist-info/METADATA
sqleval-0.2.0.dist-info/WHEEL
sqleval-0.2.0.dist-info/top_level.txt
sqleval-0.2.0.dist-info/RECORD
