Metadata-Version: 2.1
Name: sqleval
Version: 0.2.0
Summary: SQL Agent Accuracy Evaluation Framework
Author-email: Wei Xiao <weixiao@example.com>
Maintainer-email: Wei Xiao <weixiao@example.com>
License: Apache License
Project-URL: Homepage, https://github.com/sunzhaoyang/sqleval
Project-URL: Repository, https://github.com/sunzhaoyang/sqleval.git
Project-URL: Issues, https://github.com/sunzhaoyang/sqleval/issues
Keywords: sql,database,optimization,agent,evaluation,llm
Classifier: Development Status :: 3 - Alpha
Classifier: Intended Audience :: Developers
Classifier: License :: OSI Approved :: MIT License
Classifier: Operating System :: OS Independent
Classifier: Programming Language :: Python :: 3
Classifier: Programming Language :: Python :: 3.8
Classifier: Programming Language :: Python :: 3.9
Classifier: Programming Language :: Python :: 3.10
Classifier: Programming Language :: Python :: 3.11
Classifier: Programming Language :: Python :: 3.12
Classifier: Topic :: Database
Classifier: Topic :: Software Development :: Testing
Classifier: Topic :: Scientific/Engineering :: Artificial Intelligence
Requires-Python: >=3.8
License-File: LICENSE
Requires-Dist: PyMySQL>=1.0.0
Requires-Dist: python-dotenv>=1.0.0
Requires-Dist: requests>=2.28.0
Requires-Dist: jinja2>=3.1.0
Provides-Extra: dev
Requires-Dist: pytest>=7.0.0; extra == "dev"
Requires-Dist: black>=23.0.0; extra == "dev"
Requires-Dist: isort>=5.12.0; extra == "dev"
Requires-Dist: flake8>=6.0.0; extra == "dev"
